__init__.py
multtestlib.py
multtestlib-2023.4.dist-info/LICENSE
multtestlib-2023.4.dist-info/METADATA
multtestlib-2023.4.dist-info/WHEEL
multtestlib-2023.4.dist-info/top_level.txt
multtestlib-2023.4.dist-info/RECORD
