Metadata-Version: 2.1
Name: multtestlib
Version: 2023.4
Summary: Library for executing unit tests, in Python, using parallel processing.
Author-email: Ricardo Alvarenga <alvarenga.r.ricardo@gmail.com>
License: Copyright (c) 2022 Ricardo Ribeiro de Alvarenga
Project-URL: Homepage, https://github.com/alvarengaricardo/multtestlib
Classifier: Programming Language :: Python :: 3
Classifier: License :: OSI Approved :: MIT License
Classifier: Operating System :: OS Independent
Requires-Python: >=3.7
License-File: LICENSE
